{"name":"IDimXpertCounterSinkAngleDimTol","url":"/2026/english/api/swdimxpertapi/SolidWorks.Interop.swdimxpert~SolidWorks.Interop.swdimxpert.IDimXpertCounterSinkAngleDimTol.html?id=2.4.2.69","id":"2.4.2.69","parentId":"2.4.2","chmFileName":"","image":"","contextscope":"","module":"","appname":"","domain":"","quadrant":"","checkvisibility":"","urlpart":"","brand":"","guide":"","isLeaf":false,"children":[{"name":"Members","url":"/2026/english/api/swdimxpertapi/SolidWorks.Interop.swdimxpert~SolidWorks.Interop.swdimxpert.IDimXpertCounterSinkAngleDimTol_members.html?id=2.4.2.69.0","id":"2.4.2.69.0","parentId":"2.4.2.69","chmFileName":"","image":"","contextscope":"","module":"","appname":"","domain":"","quadrant":"","checkvisibility":"","urlpart":"","brand":"","guide":"","isLeaf":true,"Expanded":false,"Selected":false}],"Expanded":true,"Selected":false}