{"name":"IColorTable","url":"/2026/english/api/sldworksapi/SolidWorks.Interop.sldworks~SolidWorks.Interop.sldworks.IColorTable.html?id=2.2.1.53","id":"2.2.1.53","parentId":"2.2.1","chmFileName":"","image":"","contextscope":"","module":"","appname":"","domain":"","quadrant":"","checkvisibility":"","urlpart":"","brand":"","guide":"","isLeaf":false,"children":[{"name":"Members","url":"/2026/english/api/sldworksapi/SolidWorks.Interop.sldworks~SolidWorks.Interop.sldworks.IColorTable_members.html?id=2.2.1.53.0","id":"2.2.1.53.0","parentId":"2.2.1.53","chmFileName":"","image":"","contextscope":"","module":"","appname":"","domain":"","quadrant":"","checkvisibility":"","urlpart":"","brand":"","guide":"","isLeaf":true,"Expanded":false,"Selected":false}],"Expanded":true,"Selected":false}